LICENSE
README.md
setup.py
mp_logger_src/__init__.py
mp_logger_src/aws_logger.py
mp_logger_src/base_logger.py
mp_logger_src/file_logger.py
mp_logger_src/mongodb_logger.py
multi_python_logger/__init__.py
multi_python_logger/logger.py
multi_python_logger.egg-info/PKG-INFO
multi_python_logger.egg-info/SOURCES.txt
multi_python_logger.egg-info/dependency_links.txt
multi_python_logger.egg-info/requires.txt
multi_python_logger.egg-info/top_level.txt