Metadata-Version: 2.1
Name: multi-python-logger
Version: 3.0.0
Summary: Application to provide different logging mechanisms
Home-page: UNKNOWN
Author: Mohamed Naji Aboo
Author-email: aboonaji@gmail.com
License: UNKNOWN
Keywords: python logger cloud_logger,aws_cloudwatch_logger
Platform: UNKNOWN
License-File: LICENSE
